Workbook

Sheet 売上報告書
B2: 売 上 報 告 書
B4: 2026年7月度
B7: 株式会社サンプル商事 | I7: 作成：経営企画部 | O7: 2026年7月27日
B10: 【 概 要 】
B11: 売上合計 | G11: 目標金額 | L11: 達成率 | Q11: 前年比
B12: =F29 -> 123640000 | G12: =I29 -> 120110000 | L12: =IF(G12=0,"",B12/G12) -> 1.0293897 | Q12: =S29 -> 1.0639127
B15: 【 部門別実績 】
B17: 部門 | F17: 売上高 | I17: 目標 | L17: 達成率 | N17: 粗利益 | Q17: 粗利率 | S17: 前年比 | U17: 評価
B18: 営業第一部 | F18: =営業第一部!B10 -> 22270000 | I18: =営業第一部!F10 -> 20750000 | L18: =IF(I18=0,"",F18/I18) -> 1.073253 | N18: =営業第一部!N42 -> 6681000 | Q18: =IF(F18=0,"",N18/F18) -> 0.3 | S18: =営業第一部!N10 -> 1.05 | U18: =IF(L18="","",IF(L18>=1.05,"◎",IF(L18>=1,"○",IF(L18>=0.95,"△","×")))) -> ◎
B19: 営業第二部 | F19: =営業第二部!B10 -> 19960000 | I19: =営業第二部!F10 -> 20160000 | L19: =IF(I19=0,"",F19/I19) -> 0.99007937 | N19: =営業第二部!N42 -> 5589400 | Q19: =IF(F19=0,"",N19/F19) -> 0.28003006 | S19: =営業第二部!N10 -> 0.98 | U19: =IF(L19="","",IF(L19>=1.05,"◎",IF(L19>=1,"○",IF(L19>=0.95,"△","×")))) -> △
B20: 営業第三部 | F20: =営業第三部!B10 -> 21880000 | I20: =営業第三部!F10 -> 21300000 | L20: =IF(I20=0,"",F20/I20) -> 1.02723 | N20: =営業第三部!N42 -> 6564000 | Q20: =IF(F20=0,"",N20/F20) -> 0.3 | S20: =営業第三部!N10 -> 1.08 | U20: =IF(L20="","",IF(L20>=1.05,"◎",IF(L20>=1,"○",IF(L20>=0.95,"△","×")))) -> ○
B21: 法人営業部 | F21: =法人営業部!B10 -> 36500000 | I21: =法人営業部!F10 -> 35030000 | L21: =IF(I21=0,"",F21/I21) -> 1.041964 | N21: =法人営業部!N42 -> 9855000 | Q21: =IF(F21=0,"",N21/F21) -> 0.27 | S21: =法人営業部!N10 -> 1.12 | U21: =IF(L21="","",IF(L21>=1.05,"◎",IF(L21>=1,"○",IF(L21>=0.95,"△","×")))) -> ○
B22: 海外事業部 | F22: =海外事業部!B10 -> 11720000 | I22: =海外事業部!F10 -> 12400000 | L22: =IF(I22=0,"",F22/I22) -> 0.94516129 | N22: =海外事業部!N42 -> 2930000 | Q22: =IF(F22=0,"",N22/F22) -> 0.25 | S22: =海外事業部!N10 -> 0.92 | U22: =IF(L22="","",IF(L22>=1.05,"◎",IF(L22>=1,"○",IF(L22>=0.95,"△","×")))) -> ×
B23: EC事業部 | F23: =EC事業部!B10 -> 11310000 | I23: =EC事業部!F10 -> 10470000 | L23: =IF(I23=0,"",F23/I23) -> 1.0802292 | N23: =EC事業部!N42 -> 3958500 | Q23: =IF(F23=0,"",N23/F23) -> 0.35 | S23: =EC事業部!N10 -> 1.25 | U23: =IF(L23="","",IF(L23>=1.05,"◎",IF(L23>=1,"○",IF(L23>=0.95,"△","×")))) -> ◎
B29: 合 計 | F29: =SUM(F18:F23) -> 123640000 | I29: =SUM(I18:I23) -> 120110000 | L29: =IF(I29=0,"",F29/I29) -> 1.0293897 | N29: =SUM(N18:N23) -> 35577900 | Q29: =IF(F29=0,"",N29/F29) -> 0.28775396 | S29: {=IF(SUMPRODUCT(F18:F23/S18:S23)=0,"",F29/SUMPRODUCT(F18:F23/S18:S23))} -> 1.0639127 | U29: =IF(L29="","",IF(L29>=1.05,"◎",IF(L29>=1,"○",IF(L29>=0.95,"△","×")))) -> ○
B32: 【 備 考 】
B33: ・全社売上高は123,640,000円、目標120,110,000円に対し達成率102.9%と目標を達成 ・法人営業部が36,500,000円（全社比29.5%）と最大の貢献。達成率104.2%、前年比112.0%と好調 ・EC事業部は達成率108.0%・前年比125.0%と全部門で最も高い伸長。粗利率35.0%も全社最高 ・海外事業部は為替影響により達成率94.5%・前年比92.0%と唯一の未達。下期の挽回に注力 ・営業第二部は達成率99.0%と僅かに未達。粗利率28.0%の改善が課題
B44: 【評価基準】 ◎：達成率105%以上 / ○：100%以上 / △：95%以上 / ×：95%未満

Sheet 営業第一部
B2: 営業第一部 売上明細
B4: 2026年7月度
B8: 【 部門実績 】
B9: 売上高 | F9: 目標 | J9: 達成率 | N9: 前年比 | R9: 評価
B10: =K42 -> 22270000 | F10: 20750000 | J10: =IF(F10=0,"",B10/F10) -> 1.073253 | N10: 1.05 | R10: =IF(J10="","",IF(J10>=1.05,"◎",IF(J10>=1,"○",IF(J10>=0.95,"△","×")))) -> ◎
B12: 【 売上明細 】
B13: 日付 | D13: 顧客名 | H13: 案件名 | K13: 売上金額 | N13: 粗利益 | Q13: 粗利率 | S13: 担当者
B14: 46206 | D14: ABC商事株式会社 | H14: システム導入 | K14: 2500000 | N14: 750000 | Q14: =IF(K14=0,"",N14/K14) -> 0.3 | S14: 山田太郎
B15: 46211 | D15: DEF工業株式会社 | H15: 保守契約更新 | K15: 1200000 | N15: 360000 | Q15: =IF(K15=0,"",N15/K15) -> 0.3 | S15: 佐藤花子
B16: 46218 | D16: GHI電機株式会社 | H16: 機器販売 | K16: 1800000 | N16: 540000 | Q16: =IF(K16=0,"",N16/K16) -> 0.3 | S16: 山田太郎
B17: 46225 | D17: JKL物産株式会社 | H17: コンサル | K17: 1550000 | N17: 465000 | Q17: =IF(K17=0,"",N17/K17) -> 0.3 | S17: 鈴木一郎
B18: 46231 | D18: MNO建設株式会社 | H18: 追加開発 | K18: 1000000 | N18: 300000 | Q18: =IF(K18=0,"",N18/K18) -> 0.3 | S18: 佐藤花子
B19: 46202 | D19: PQR商事株式会社 | H19: 機器販売 | K19: 1350000 | N19: 405000 | Q19: =IF(K19=0,"",N19/K19) -> 0.3 | S19: 山田太郎
B20: 46205 | D20: STU電子株式会社 | H20: 保守契約 | K20: 980000 | N20: 294000 | Q20: =IF(K20=0,"",N20/K20) -> 0.3 | S20: 鈴木一郎
B21: 46209 | D21: VWX物流株式会社 | H21: システム開発 | K21: 2100000 | N21: 630000 | Q21: =IF(K21=0,"",N21/K21) -> 0.3 | S21: 佐藤花子
B22: 46213 | D22: YZA化学株式会社 | H22: コンサル | K22: 1150000 | N22: 345000 | Q22: =IF(K22=0,"",N22/K22) -> 0.3 | S22: 山田太郎
B23: 46216 | D23: BCD食品株式会社 | H23: 追加開発 | K23: 750000 | N23: 225000 | Q23: =IF(K23=0,"",N23/K23) -> 0.3 | S23: 鈴木一郎
B24: 46220 | D24: EFG製薬株式会社 | H24: 大型案件 | K24: 2800000 | N24: 840000 | Q24: =IF(K24=0,"",N24/K24) -> 0.3 | S24: 佐藤花子
B25: 46223 | D25: HIJ機械株式会社 | H25: 機器販売 | K25: 1680000 | N25: 504000 | Q25: =IF(K25=0,"",N25/K25) -> 0.3 | S25: 山田太郎
... B28: 46232 | D28: QRS金属株式会社 | H28: 追加開発 | K28: 1100000 | N28: 330000 | Q28: =IF(K28=0,"",N28/K28) -> 0.3 | S28: 山田太郎
B42: 合 計 | K42: =SUM(K14:M34) -> 22270000 | N42: =SUM(N14:P34) -> 6681000 | Q42: =IF(K42=0,"",N42/K42) -> 0.3

Sheet 営業第二部
B2: 営業第二部 売上明細
B4: 2026年7月度
B8: 【 部門実績 】
B9: 売上高 | F9: 目標 | J9: 達成率 | N9: 前年比 | R9: 評価
B10: =K42 -> 19960000 | F10: 20160000 | J10: =IF(F10=0,"",B10/F10) -> 0.99007937 | N10: 0.98 | R10: =IF(J10="","",IF(J10>=1.05,"◎",IF(J10>=1,"○",IF(J10>=0.95,"△","×")))) -> △
B12: 【 売上明細 】
B13: 日付 | D13: 顧客名 | H13: 案件名 | K13: 売上金額 | N13: 粗利益 | Q13: 粗利率 | S13: 担当者
B14: 46208 | D14: PQR商事株式会社 | H14: 機器販売 | K14: 1800000 | N14: 504000 | Q14: =IF(K14=0,"",N14/K14) -> 0.28 | S14: 田中健一
B15: 46215 | D15: STU工業株式会社 | H15: 保守契約 | K15: 1500000 | N15: 420000 | Q15: =IF(K15=0,"",N15/K15) -> 0.28 | S15: 高橋美咲
B16: 46221 | D16: VWX電機株式会社 | H16: システム | K16: 1330000 | N16: 372400 | Q16: =IF(K16=0,"",N16/K16) -> 0.28 | S16: 田中健一
B17: 46228 | D17: YZA物産株式会社 | H17: コンサル | K17: 1200000 | N17: 336000 | Q17: =IF(K17=0,"",N17/K17) -> 0.28 | S17: 渡辺誠
B18: 46233 | D18: BCD建設株式会社 | H18: 追加開発 | K18: 800000 | N18: 224600 | Q18: =IF(K18=0,"",N18/K18) -> 0.28075 | S18: 高橋美咲
B19: 46203 | D19: EFG商事株式会社 | H19: システム開発 | K19: 1450000 | N19: 406000 | Q19: =IF(K19=0,"",N19/K19) -> 0.28 | S19: 田中健一
B20: 46207 | D20: HIJ電子株式会社 | H20: 大型案件 | K20: 2200000 | N20: 616000 | Q20: =IF(K20=0,"",N20/K20) -> 0.28 | S20: 高橋美咲
B21: 46210 | D21: KLM物流株式会社 | H21: 機器販売 | K21: 1100000 | N21: 308000 | Q21: =IF(K21=0,"",N21/K21) -> 0.28 | S21: 渡辺誠
B22: 46214 | D22: NOP化学株式会社 | H22: 保守契約 | K22: 950000 | N22: 266000 | Q22: =IF(K22=0,"",N22/K22) -> 0.28 | S22: 田中健一
B23: 46217 | D23: QRS食品株式会社 | H23: コンサル | K23: 780000 | N23: 218400 | Q23: =IF(K23=0,"",N23/K23) -> 0.28 | S23: 高橋美咲
B24: 46221 | D24: TUV製薬株式会社 | H24: 追加開発 | K24: 1650000 | N24: 462000 | Q24: =IF(K24=0,"",N24/K24) -> 0.28 | S24: 渡辺誠
B25: 46224 | D25: WXY機械株式会社 | H25: システム | K25: 1380000 | N25: 386400 | Q25: =IF(K25=0,"",N25/K25) -> 0.28 | S25: 田中健一
... B28: 46233 | D28: FGH金属株式会社 | H28: 大型案件 | K28: 1850000 | N28: 518000 | Q28: =IF(K28=0,"",N28/K28) -> 0.28 | S28: 田中健一
B42: 合 計 | K42: =SUM(K14:K28) -> 19960000 | N42: =SUM(N14:N28) -> 5589400 | Q42: =IF(K42=0,"",N42/K42) -> 0.28003006

Sheet 営業第三部
B2: 営業第三部 売上明細
B4: 2026年7月度
B8: 【 部門実績 】
B9: 売上高 | F9: 目標 | J9: 達成率 | N9: 前年比 | R9: 評価
B10: =K42 -> 21880000 | F10: 21300000 | J10: =IF(F10=0,"",B10/F10) -> 1.02723 | N10: 1.08 | R10: =IF(J10="","",IF(J10>=1.05,"◎",IF(J10>=1,"○",IF(J10>=0.95,"△","×")))) -> ○
B12: 【 売上明細 】
B13: 日付 | D13: 顧客名 | H13: 案件名 | K13: 売上金額 | N13: 粗利益 | Q13: 粗利率 | S13: 担当者
B14: 46205 | D14: EFG商事株式会社 | H14: 大型案件 | K14: 2200000 | N14: 660000 | Q14: =IF(K14=0,"",N14/K14) -> 0.3 | S14: 木村大輔
B15: 46213 | D15: HIJ工業株式会社 | H15: 機器販売 | K15: 1600000 | N15: 480000 | Q15: =IF(K15=0,"",N15/K15) -> 0.3 | S15: 中村真理
B16: 46219 | D16: KLM電機株式会社 | H16: 保守契約 | K16: 1400000 | N16: 420000 | Q16: =IF(K16=0,"",N16/K16) -> 0.3 | S16: 木村大輔
B17: 46226 | D17: NOP物産株式会社 | H17: システム | K17: 1500000 | N17: 450000 | Q17: =IF(K17=0,"",N17/K17) -> 0.3 | S17: 伊藤裕子
B18: 46232 | D18: QRS建設株式会社 | H18: コンサル | K18: 1000000 | N18: 300000 | Q18: =IF(K18=0,"",N18/K18) -> 0.3 | S18: 中村真理
B19: 46204 | D19: TUV商事株式会社 | H19: 機器販売 | K19: 1550000 | N19: 465000 | Q19: =IF(K19=0,"",N19/K19) -> 0.3 | S19: 木村大輔
B20: 46208 | D20: WXY電子株式会社 | H20: 保守契約 | K20: 1100000 | N20: 330000 | Q20: =IF(K20=0,"",N20/K20) -> 0.3 | S20: 中村真理
B21: 46212 | D21: ZAB物流株式会社 | H21: システム開発 | K21: 1900000 | N21: 570000 | Q21: =IF(K21=0,"",N21/K21) -> 0.3 | S21: 伊藤裕子
B22: 46215 | D22: CDE化学株式会社 | H22: コンサル | K22: 1250000 | N22: 375000 | Q22: =IF(K22=0,"",N22/K22) -> 0.3 | S22: 木村大輔
B23: 46219 | D23: FGH食品株式会社 | H23: 追加開発 | K23: 850000 | N23: 255000 | Q23: =IF(K23=0,"",N23/K23) -> 0.3 | S23: 中村真理
B24: 46222 | D24: IJK製薬株式会社 | H24: 大型案件 | K24: 2400000 | N24: 720000 | Q24: =IF(K24=0,"",N24/K24) -> 0.3 | S24: 伊藤裕子
B25: 46225 | D25: LMN機械株式会社 | H25: 機器販売 | K25: 1350000 | N25: 405000 | Q25: =IF(K25=0,"",N25/K25) -> 0.3 | S25: 木村大輔
... B28: 46234 | D28: UVW金属株式会社 | H28: 追加開発 | K28: 1180000 | N28: 354000 | Q28: =IF(K28=0,"",N28/K28) -> 0.3 | S28: 木村大輔
B42: 合 計 | K42: =SUM(K14:K28) -> 21880000 | N42: =SUM(N14:N28) -> 6564000 | Q42: =IF(K42=0,"",N42/K42) -> 0.3

Sheet 法人営業部
B2: 法人営業部 売上明細
B4: 2026年7月度
B8: 【 部門実績 】
B9: 売上高 | F9: 目標 | J9: 達成率 | N9: 前年比 | R9: 評価
B10: =K42 -> 36500000 | F10: 35030000 | J10: =IF(F10=0,"",B10/F10) -> 1.041964 | N10: 1.12 | R10: =IF(J10="","",IF(J10>=1.05,"◎",IF(J10>=1,"○",IF(J10>=0.95,"△","×")))) -> ○
B12: 【 売上明細 】
B13: 日付 | D13: 顧客名 | H13: 案件名 | K13: 売上金額 | N13: 粗利益 | Q13: 粗利率 | S13: 担当者
B14: 46204 | D14: 大手製造A社 | H14: 基幹システム | K14: 4500000 | N14: 1215000 | Q14: =IF(K14=0,"",N14/K14) -> 0.27 | S14: 吉田正明
B15: 46211 | D15: 大手金融B社 | H15: セキュリティ | K15: 3200000 | N15: 864000 | Q15: =IF(K15=0,"",N15/K15) -> 0.27 | S15: 小林秀樹
B16: 46218 | D16: 大手流通C社 | H16: クラウド移行 | K16: 2500000 | N16: 675000 | Q16: =IF(K16=0,"",N16/K16) -> 0.27 | S16: 吉田正明
B17: 46225 | D17: 大手通信D社 | H17: 保守契約 | K17: 1500000 | N17: 405000 | Q17: =IF(K17=0,"",N17/K17) -> 0.27 | S17: 松本愛子
B18: 46231 | D18: 大手商社E社 | H18: 追加開発 | K18: 800000 | N18: 216000 | Q18: =IF(K18=0,"",N18/K18) -> 0.27 | S18: 小林秀樹
B19: 46203 | D19: 大手製造F社 | H19: システム開発 | K19: 3200000 | N19: 864000 | Q19: =IF(K19=0,"",N19/K19) -> 0.27 | S19: 吉田正明
B20: 46207 | D20: 大手金融G社 | H20: セキュリティ | K20: 2800000 | N20: 756000 | Q20: =IF(K20=0,"",N20/K20) -> 0.27 | S20: 小林秀樹
B21: 46210 | D21: 大手流通H社 | H21: クラウド移行 | K21: 2100000 | N21: 567000 | Q21: =IF(K21=0,"",N21/K21) -> 0.27 | S21: 松本愛子
B22: 46214 | D22: 大手通信I社 | H22: 保守契約 | K22: 1800000 | N22: 486000 | Q22: =IF(K22=0,"",N22/K22) -> 0.27 | S22: 吉田正明
B23: 46217 | D23: 大手商社J社 | H23: 追加開発 | K23: 1500000 | N23: 405000 | Q23: =IF(K23=0,"",N23/K23) -> 0.27 | S23: 小林秀樹
B24: 46221 | D24: 大手製造K社 | H24: 基幹システム | K24: 3500000 | N24: 945000 | Q24: =IF(K24=0,"",N24/K24) -> 0.27 | S24: 松本愛子
B25: 46224 | D25: 大手金融L社 | H25: データ分析 | K25: 2400000 | N25: 648000 | Q25: =IF(K25=0,"",N25/K25) -> 0.27 | S25: 吉田正明
... B28: 46233 | D28: 大手商社O社 | H28: DX推進 | K28: 2600000 | N28: 702000 | Q28: =IF(K28=0,"",N28/K28) -> 0.27 | S28: 吉田正明
B42: 合 計 | K42: =SUM(K14:K28) -> 36500000 | N42: =SUM(N14:N28) -> 9855000 | Q42: =IF(K42=0,"",N42/K42) -> 0.27

Sheet 海外事業部
B2: 海外事業部 売上明細
B4: 2026年7月度
B8: 【 部門実績 】
B9: 売上高 | F9: 目標 | J9: 達成率 | N9: 前年比 | R9: 評価
B10: =K42 -> 11720000 | F10: 12400000 | J10: =IF(F10=0,"",B10/F10) -> 0.94516129 | N10: 0.92 | R10: =IF(J10="","",IF(J10>=1.05,"◎",IF(J10>=1,"○",IF(J10>=0.95,"△","×")))) -> ×
B12: 【 売上明細 】
B13: 日付 | D13: 顧客名 | H13: 案件名 | K13: 売上金額 | N13: 粗利益 | Q13: 粗利率 | S13: 担当者
B14: 46207 | D14: 米国Alpha Corp | H14: 現地販売 | K14: 1500000 | N14: 375000 | Q14: =IF(K14=0,"",N14/K14) -> 0.25 | S14: 加藤健太
B15: 46214 | D15: 欧州Beta GmbH | H15: 技術支援 | K15: 1200000 | N15: 300000 | Q15: =IF(K15=0,"",N15/K15) -> 0.25 | S15: 斎藤由美
B16: 46221 | D16: 中国Gamma社 | H16: 機器輸出 | K16: 1100000 | N16: 275000 | Q16: =IF(K16=0,"",N16/K16) -> 0.25 | S16: 加藤健太
B17: 46227 | D17: 韓国Delta Co. | H17: 保守契約 | K17: 900000 | N17: 225000 | Q17: =IF(K17=0,"",N17/K17) -> 0.25 | S17: 斎藤由美
B18: 46233 | D18: 台湾Epsilon Ltd | H18: コンサル | K18: 500000 | N18: 125000 | Q18: =IF(K18=0,"",N18/K18) -> 0.25 | S18: 加藤健太
B19: 46203 | D19: 米国現地法人A | H19: システム開発 | K19: 850000 | N19: 212500 | Q19: =IF(K19=0,"",N19/K19) -> 0.25 | S19: 山本太一
B20: 46207 | D20: 欧州販売代理店B | H20: 機器販売 | K20: 720000 | N20: 180000 | Q20: =IF(K20=0,"",N20/K20) -> 0.25 | S20: 加藤明美
B21: 46210 | D21: アジア現地法人C | H21: 保守契約 | K21: 650000 | N21: 162500 | Q21: =IF(K21=0,"",N21/K21) -> 0.25 | S21: 佐々木健
B22: 46214 | D22: 中国販売代理店D | H22: コンサル | K22: 580000 | N22: 145000 | Q22: =IF(K22=0,"",N22/K22) -> 0.25 | S22: 山本太一
B23: 46217 | D23: 韓国現地法人E | H23: 追加開発 | K23: 490000 | N23: 122500 | Q23: =IF(K23=0,"",N23/K23) -> 0.25 | S23: 加藤明美
B24: 46221 | D24: 東南アジア支社F | H24: システム | K24: 750000 | N24: 187500 | Q24: =IF(K24=0,"",N24/K24) -> 0.25 | S24: 佐々木健
B25: 46224 | D25: インド販売代理店G | H25: 機器販売 | K25: 620000 | N25: 155000 | Q25: =IF(K25=0,"",N25/K25) -> 0.25 | S25: 山本太一
... B28: 46233 | D28: 南米販売代理店J | H28: コンサル | K28: 450000 | N28: 112500 | Q28: =IF(K28=0,"",N28/K28) -> 0.25 | S28: 山本太一
B42: 合 計 | K42: =SUM(K14:K28) -> 11720000 | N42: =SUM(N14:N28) -> 2930000 | Q42: =IF(K42=0,"",N42/K42) -> 0.25

Sheet EC事業部
B2: EC事業部 売上明細
B4: 2026年7月度
B8: 【 部門実績 】
B9: 売上高 | F9: 目標 | J9: 達成率 | N9: 前年比 | R9: 評価
B10: =K42 -> 11310000 | F10: 10470000 | J10: =IF(F10=0,"",B10/F10) -> 1.0802292 | N10: 1.25 | R10: =IF(J10="","",IF(J10>=1.05,"◎",IF(J10>=1,"○",IF(J10>=0.95,"△","×")))) -> ◎
B12: 【 売上明細 】
B13: 日付 | D13: 顧客名 | H13: 案件名 | K13: 売上金額 | N13: 粗利益 | Q13: 粗利率 | S13: 担当者
B14: 46206 | D14: 楽天市場 | H14: 月間売上 | K14: 1200000 | N14: 420000 | Q14: =IF(K14=0,"",N14/K14) -> 0.35 | S14: 森田拓也
B15: 46213 | D15: Amazon | H15: 月間売上 | K15: 1100000 | N15: 385000 | Q15: =IF(K15=0,"",N15/K15) -> 0.35 | S15: 森田拓也
B16: 46220 | D16: Yahoo!ショッピング | H16: 月間売上 | K16: 850000 | N16: 297500 | Q16: =IF(K16=0,"",N16/K16) -> 0.35 | S16: 岡田麻衣
B17: 46227 | D17: 自社ECサイト | H17: 月間売上 | K17: 700000 | N17: 245000 | Q17: =IF(K17=0,"",N17/K17) -> 0.35 | S17: 岡田麻衣
B18: 46234 | D18: その他モール | H18: 月間売上 | K18: 470000 | N18: 164500 | Q18: =IF(K18=0,"",N18/K18) -> 0.35 | S18: 森田拓也
B19: 46203 | D19: ECモールA出店 | H19: 広告運用 | K19: 620000 | N19: 217000 | Q19: =IF(K19=0,"",N19/K19) -> 0.35 | S19: 井上真司
B20: 46207 | D20: 自社ECサイトB | H20: システム改修 | K20: 850000 | N20: 297500 | Q20: =IF(K20=0,"",N20/K20) -> 0.35 | S20: 藤田優子
B21: 46210 | D21: ECモールC出店 | H21: 商品登録 | K21: 480000 | N21: 168000 | Q21: =IF(K21=0,"",N21/K21) -> 0.35 | S21: 斎藤隆
B22: 46214 | D22: 自社ECサイトD | H22: プロモ | K22: 720000 | N22: 252000 | Q22: =IF(K22=0,"",N22/K22) -> 0.35 | S22: 井上真司
B23: 46217 | D23: ECモールE出店 | H23: 広告運用 | K23: 550000 | N23: 192500 | Q23: =IF(K23=0,"",N23/K23) -> 0.35 | S23: 藤田優子
B24: 46221 | D24: 越境ECサイトF | H24: 多言語対応 | K24: 980000 | N24: 343000 | Q24: =IF(K24=0,"",N24/K24) -> 0.35 | S24: 斎藤隆
B25: 46224 | D25: ECモールG出店 | H25: 商品登録 | K25: 420000 | N25: 147000 | Q25: =IF(K25=0,"",N25/K25) -> 0.35 | S25: 井上真司
... B28: 46233 | D28: 越境ECサイトJ | H28: 大型案件 | K28: 1100000 | N28: 385000 | Q28: =IF(K28=0,"",N28/K28) -> 0.35 | S28: 井上真司
B42: 合 計 | K42: =SUM(K14:K28) -> 11310000 | N42: =SUM(N14:N28) -> 3958500 | Q42: =IF(K42=0,"",N42/K42) -> 0.35
